pyquizlet/__init__.py
pyquizlet/curl.py
pyquizlet/flashcards.py
pyquizlet-0.0.1.dist-info/LICENSE
pyquizlet-0.0.1.dist-info/METADATA
pyquizlet-0.0.1.dist-info/WHEEL
pyquizlet-0.0.1.dist-info/top_level.txt
pyquizlet-0.0.1.dist-info/RECORD
