Metadata-Version: 2.1
Name: pyquizlet
Version: 0.0.1
Summary: An unofficial/reverse-engineered Quizlet API
Author: Rohan Gupta
Project-URL: Homepage, https://github.com/simplyrohan/pyquizlet/
Project-URL: Issues, https://github.com/simplyrohan/pyquizlet/issues
Classifier: Programming Language :: Python :: 3
Classifier: License :: OSI Approved :: MIT License
Classifier: Operating System :: OS Independent
Requires-Python: >=3.8
License-File: LICENSE
